rosey_power/__init__.py
rosey_power-0.20201216.1.dist-info/METADATA
rosey_power-0.20201216.1.dist-info/WHEEL
rosey_power-0.20201216.1.dist-info/top_level.txt
rosey_power-0.20201216.1.dist-info/RECORD
