Metadata-Version: 2.1
Name: rosey-power
Version: 0.20201216.1
Summary: Finally, easy power analysis
Home-page: https://github.com/arose13/rosey-power
Author: Stephen Anthony Rose
Author-email: me@stephenro.se
License: BSD
Download-URL: https://github.com/arose13/rosey-power/tarball/0.20201216.1
Keywords: statistics
Platform: UNKNOWN
Classifier: Development Status :: 4 - Beta
Classifier: Intended Audience :: Developers
Classifier: Programming Language :: Python :: 3
Classifier: Topic :: Scientific/Engineering :: Artificial Intelligence
Requires-Dist: numpy
Requires-Dist: pandas
Requires-Dist: tqdm
